djangorestframework_last_modified-0.1.0.dist-info/DESCRIPTION.rst
djangorestframework_last_modified-0.1.0.dist-info/METADATA
djangorestframework_last_modified-0.1.0.dist-info/metadata.json
djangorestframework_last_modified-0.1.0.dist-info/RECORD
djangorestframework_last_modified-0.1.0.dist-info/top_level.txt
djangorestframework_last_modified-0.1.0.dist-info/WHEEL
last_modified/__init__.py
last_modified/decorators.py
last_modified/__pycache__/__init__.cpython-34.pyc
last_modified/__pycache__/decorators.cpython-34.pyc
