Metadata-Version: 2.0
Name: djangorestframework-last-modified
Version: 0.1.0
Summary: Last Modified header support for Django Rest Framework.
Home-page: https://github.com/jatir/django-rest-framework-last-modified
Author: Josh Atir
Author-email: joshatir@gmail.com
License: BSD
Platform: UNKNOWN
Classifier: Development Status :: 4 - Beta
Classifier: Environment :: Web Environment
Classifier: Framework :: Django
Classifier: Intended Audience :: Developers
Classifier: License :: OSI Approved :: BSD License
Classifier: Operating System :: OS Independent
Classifier: Natural Language :: English
Classifier: Programming Language :: Python :: 3
Classifier: Programming Language :: Python :: 3.4
Classifier: Topic :: Internet :: WWW/HTTP
